MANIFEST.in
README.rst
setup.py
genderly/__init__.py
genderly/prediction.py
genderly/training.py
genderly.egg-info/.DS_Store
genderly.egg-info/PKG-INFO
genderly.egg-info/SOURCES.txt
genderly.egg-info/dependency_links.txt
genderly.egg-info/not-zip-safe
genderly.egg-info/top_level.txt
genderly/data/list_NameGender.csv
genderly/data/list_NameGender.json
genderly/model/genderPredictionModel.pkl
genderly/model/genderPredictionModel.pkl_01.npy
genderly/model/genderPredictionModel.pkl_02.npy
genderly/model/genderPredictionModel.pkl_03.npy
genderly/model/genderPredictionModel.pkl_04.npy
genderly/model/genderPredictionModel.pkl_05.npy
genderly/model/genderPredictionModel.pkl_06.npy
genderly/model/genderPredictionModel.pkl_07.npy
genderly/model/genderPredictionModel.pkl_08.npy
genderly/model/genderPredictionModel.pkl_09.npy
genderly/model/genderPredictionModel.pkl_10.npy
genderly/model/genderPredictionModel.pkl_11.npy
genderly/model/genderPredictionModel.pkl_12.npy
genderly/model/genderPredictionModel.pkl_13.npy
genderly/model/genderPredictionModel.pkl_14.npy
genderly/model/genderPredictionModel.pkl_15.npy
genderly/model/genderPredictionModel.pkl_16.npy
genderly/model/genderPredictionModel.pkl_17.npy
genderly/model/genderPredictionModel.pkl_18.npy
genderly/model/genderPredictionModel.pkl_19.npy
genderly/model/genderPredictionModel.pkl_20.npy
genderly/model/genderPredictionModel.pkl_21.npy
genderly/model/genderPredictionModel.pkl_22.npy
genderly/model/genderPredictionModel.pkl_23.npy
genderly/model/genderPredictionModel.pkl_24.npy
genderly/model/genderPredictionModel.pkl_25.npy
genderly/model/genderPredictionModel.pkl_26.npy
genderly/model/genderPredictionModel.pkl_27.npy
genderly/model/genderPredictionModel.pkl_28.npy
genderly/model/genderPredictionModel.pkl_29.npy
genderly/model/genderPredictionModel.pkl_30.npy
genderly/model/genderPredictionModel.pkl_31.npy
genderly/model/genderPredictionModel.pkl_32.npy
genderly/model/genderPredictionModel.pkl_33.npy
genderly/model/genderPredictionModel.pkl_34.npy
genderly/model/genderPredictionModel.pkl_35.npy
genderly/model/genderPredictionModel.pkl_36.npy
genderly/model/genderPredictionModel.pkl_37.npy
