Metadata-Version: 1.0
Name: genderly
Version: 0.106
Summary: A library to classify an indian name as Male or Female. Mainly focused around making the user onboarding smooth for eCommerce merchants by pre-filling the gender for their users during a signup.
Home-page: https://github.com/israjsingh/genderly
Author: Raj Vardhan Singh
Author-email: is.rajvardhan@gmail.com
License: MIT
Keywords: gender,classification,prediction
Platform: UNKNOWN
